{
  "parent": "ic2r:ic2r/root",
  "display": {
    "icon": {
      "id": "ic2r:resin"
    },
    "title": {
      "translate": "advancements.ic2r.acquire_resin"
    },
    "description": {
      "translate": "advancements.ic2r.acquire_resin.desc"
    },
    "frame": "task",
    "show_toast": true,
    "announce_to_chat": true,
    "hidden": false
  },
  "criteria": {
    "ic2r:resin": {
      "trigger": "minecraft:inventory_changed",
      "conditions": {
        "items": [
          {
            "items": [
              "ic2r:resin"
            ]
          }
        ]
      }
    }
  },
  "requirements": [
    [
      "ic2r:resin"
    ]
  ]
}